cloud_tpu_diagnostics/__init__.py
cloud_tpu_diagnostics/configuration.py
cloud_tpu_diagnostics/diagnostic.py
cloud_tpu_diagnostics/src/debug.py
cloud_tpu_diagnostics/src/diagnose.py
cloud_tpu_diagnostics/src/stack_trace.py
cloud_tpu_diagnostics/src/config/debug_configuration.py
cloud_tpu_diagnostics/src/config/diagnostic_configuration.py
cloud_tpu_diagnostics/src/config/stack_trace_configuration.py
cloud_tpu_diagnostics/src/util/default.py
cloud_tpu_diagnostics/src/util/stack_trace_test_util.py
cloud_tpu_diagnostics/tests/debug_test.py
cloud_tpu_diagnostics/tests/diagnose_test.py
cloud_tpu_diagnostics/tests/stack_trace_test.py
cloud_tpu_diagnostics-1.1.14.dist-info/WHEEL
cloud_tpu_diagnostics-1.1.14.dist-info/METADATA
cloud_tpu_diagnostics-1.1.14.dist-info/RECORD
