Metadata-Version: 2.1
Name: cloud-tpu-diagnostics
Version: 1.1.14
Summary: Monitor, debug and profile the jobs running on Cloud TPU.
Keywords: 
Author-email: Cloud TPU Team <cloud-tpu-eng@google.com>
Requires-Python: >=3.8
Classifier: Programming Language :: Python :: 3.8
Classifier: Programming Language :: Python :: 3.9
Classifier: Programming Language :: Python :: 3.10
Classifier: Programming Language :: Python :: 3.11
Project-URL: Bug Tracker, https://github.com/google/cloud-tpu-monitoring-debugging/issues
Project-URL: Homepage, https://github.com/google/cloud-tpu-monitoring-debugging
